LICENSE
README.md
odmantic/__init__.py
odmantic/bson.py
odmantic/config.py
odmantic/engine.py
odmantic/exceptions.py
odmantic/fastapi.py
odmantic/field.py
odmantic/model.py
odmantic/py.typed
odmantic/query.py
odmantic/reference.py
odmantic/typing.py
odmantic/utils.py
odmanticti-0.4.1b2.dist-info/LICENSE
odmanticti-0.4.1b2.dist-info/WHEEL
odmanticti-0.4.1b2.dist-info/METADATA
odmanticti-0.4.1b2.dist-info/RECORD
