Metadata-Version: 2.1
Name: odmanticti
Version: 0.4.1b2
Summary: ODMantic, an AsyncIO MongoDB Object Document Mapper for Python using type hints 
Home-page: https://github.com/tangibleintelligence/odmantic
License: ISC
Keywords: mongodb,asyncio,types,pydantic,motor
Author: Arthur Pastel
Author-email: arthur.pastel@gmail.com
Requires-Python: >=3.6,<4.0
Classifier: Development Status :: 4 - Beta
Classifier: Environment :: Web Environment
Classifier: Framework :: AsyncIO
Classifier: Intended Audience :: Developers
Classifier: Intended Audience :: Information Technology
Classifier: Intended Audience :: System Administrators
Classifier: License :: OSI Approved
Classifier: License :: OSI Approved :: ISC License (ISCL)
Classifier: Operating System :: OS Independent
Classifier: Programming Language :: Python
Classifier: Programming Language :: Python :: 3
Classifier: Programming Language :: Python :: 3 :: Only
Classifier: Programming Language :: Python :: 3.10
Classifier: Programming Language :: Python :: 3.6
Classifier: Programming Language :: Python :: 3.7
Classifier: Programming Language :: Python :: 3.8
Classifier: Programming Language :: Python :: 3.9
Classifier: Programming Language :: Python :: Implementation :: CPython
Classifier: Topic :: Database
Classifier: Topic :: Database :: Front-Ends
Classifier: Topic :: Internet
Classifier: Topic :: Software Development
Classifier: Topic :: Software Development :: Libraries
Classifier: Topic :: Software Development :: Libraries :: Python Modules
Classifier: Topic :: Software Development :: Object Brokering
Classifier: Typing :: Typed
Provides-Extra: fastapi
Requires-Dist: fastapi (>=0.61.1,<0.69.0); extra == "fastapi"
Requires-Dist: importlib-metadata (>=1,<5); python_version < "3.8"
Requires-Dist: motor (>=2.1.0,<2.6.0)
Requires-Dist: pydantic (>=1.6.2,!=1.7,!=1.7.1,!=1.7.2,!=1.7.3,!=1.8,!=1.8.1,<1.9.0)
Requires-Dist: typing-extensions (>=3.7.4.3,<4.0.0.0); python_version < "3.8"
Project-URL: Documentation, https://art049.github.io/odmantic
Project-URL: Repository, https://github.com/tangibleintelligence/odmantic
